nvsonar/__init__.py
nvsonar/__main__.py
nvsonar/cli.py
nvsonar/core/__init__.py
nvsonar/core/monitor.py
nvsonar/tui/__init__.py
nvsonar/tui/app.py
nvsonar/utils/__init__.py
nvsonar/utils/gpu_info.py
nvsonar-1.0.2.dist-info/licenses/LICENSE
nvsonar-1.0.2.dist-info/METADATA
nvsonar-1.0.2.dist-info/WHEEL
nvsonar-1.0.2.dist-info/entry_points.txt
nvsonar-1.0.2.dist-info/top_level.txt
nvsonar-1.0.2.dist-info/RECORD
