Metadata-Version: 2.4
Name: nvsonar
Version: 1.0.2
Summary: Active GPU diagnostic tool that identifies performance bottlenecks
Author: Bekmukhamed Tursunbayev, Varvara Bondarenko
License: Apache-2.0
Project-URL: Homepage, https://btursunbayev.github.io
Project-URL: Repository, https://github.com/btursunbayev/nvsonar
Keywords: gpu,cuda,nvidia,monitoring,diagnostics,performance
Classifier: Development Status :: 4 - Beta
Classifier: Environment :: Console
Classifier: Intended Audience :: Developers
Classifier: Intended Audience :: Science/Research
Classifier: License :: OSI Approved :: Apache Software License
Classifier: Operating System :: POSIX :: Linux
Classifier: Programming Language :: Python :: 3
Classifier: Programming Language :: Python :: 3.10
Classifier: Programming Language :: Python :: 3.11
Classifier: Programming Language :: Python :: 3.12
Classifier: Topic :: System :: Monitoring
Classifier: Topic :: System :: Hardware
Classifier: Topic :: Scientific/Engineering
Requires-Python: >=3.10
License-File: LICENSE
Requires-Dist: nvidia-ml-py>=12.535.0
Requires-Dist: typer>=0.9.0
Requires-Dist: rich>=13.0.0
Requires-Dist: textual>=0.47.0
Dynamic: license-file
